./.gitignore
./LICENSE
./PKG-INFO
./README.md
./pyproject.toml
./unipile_linkedin.py
unipile_linkedin_mcp-0.1.0.dist-info/METADATA
unipile_linkedin_mcp-0.1.0.dist-info/WHEEL
unipile_linkedin_mcp-0.1.0.dist-info/entry_points.txt
unipile_linkedin_mcp-0.1.0.dist-info/licenses/LICENSE
unipile_linkedin_mcp-0.1.0.dist-info/RECORD
