Metadata-Version: 2.4
Name: unipile-linkedin-mcp
Version: 0.1.0
Summary: MCP server for Unipile LinkedIn API - LinkedIn search, messaging, connections, and Sales Navigator features
Project-URL: Homepage, https://github.com/bhaktatejas922/unipile-linkedin-mcp
Project-URL: Repository, https://github.com/bhaktatejas922/unipile-linkedin-mcp
Project-URL: Issues, https://github.com/bhaktatejas922/unipile-linkedin-mcp/issues
Author-email: Tejas Bhakta <bhaktatejas922@gmail.com>
License-Expression: MIT
License-File: LICENSE
Keywords: ai,automation,linkedin,mcp,sales-navigator,unipile
Classifier: Development Status :: 4 - Beta
Classifier: Intended Audience :: Developers
Classifier: License :: OSI Approved :: MIT License
Classifier: Programming Language :: Python :: 3
Classifier: Programming Language :: Python :: 3.10
Classifier: Programming Language :: Python :: 3.11
Classifier: Programming Language :: Python :: 3.12
Classifier: Programming Language :: Python :: 3.13
Requires-Python: >=3.10
Requires-Dist: httpx>=0.25.0
Requires-Dist: mcp>=1.0.0
Requires-Dist: python-dotenv>=1.0.0
